openbb_chat/__init__.py
openbb_chat/eval.py
openbb_chat/train.py
openbb_chat/classifiers/__init__.py
openbb_chat/classifiers/abstract_zeroshot_classifier.py
openbb_chat/classifiers/roberta.py
openbb_chat/classifiers/stransformer.py
openbb_chat/data/__init__.py
openbb_chat/data/mnist_datamodule.py
openbb_chat/data/components/__init__.py
openbb_chat/kernels/__init__.py
openbb_chat/kernels/auto_llama_index.py
openbb_chat/kernels/auto_multistep_query_engine.py
openbb_chat/llms/__init__.py
openbb_chat/llms/chat_model_llm_iface.py
openbb_chat/llms/guidance_wrapper.py
openbb_chat/models/__init__.py
openbb_chat/models/mnist_module.py
openbb_chat/models/components/__init__.py
openbb_chat/models/components/simple_dense_net.py
openbb_chat/retrievers/__init__.py
openbb_chat/retrievers/hybrid_or_retriever.py
openbb_chat/utils/__init__.py
openbb_chat/utils/instantiators.py
openbb_chat/utils/logging_utils.py
openbb_chat/utils/pylogger.py
openbb_chat/utils/rich_utils.py
openbb_chat/utils/utils.py
openbb_chat-0.0.11.post1.dist-info/METADATA
openbb_chat-0.0.11.post1.dist-info/WHEEL
openbb_chat-0.0.11.post1.dist-info/RECORD
