Metadata-Version: 2.3
Name: openbb-chat
Version: 0.0.11.post1
Summary: Deep learning package to add chat capabilities to OpenBB
Project-URL: Homepage, https://github.com/GPTStonks/openbb-chat
Project-URL: Bug Tracker, https://github.com/GPTStonks/openbb-chat/issues
Author-email: GPTStonks <gptstonks@gmail.com>
Classifier: License :: OSI Approved :: MIT License
Classifier: Operating System :: OS Independent
Classifier: Programming Language :: Python :: 3
Requires-Python: <3.12,>=3.10
Requires-Dist: langchain>=0.0.353
Requires-Dist: llama-index-llms-openai>=0.1.6
Requires-Dist: llama-index-retrievers-bm25>=0.1.3
Requires-Dist: llama-index>=0.10.13
Requires-Dist: rank-bm25>=0.2.2
Provides-Extra: advanced
Requires-Dist: accelerate>=0.22.0; extra == 'advanced'
Requires-Dist: auto-gptq>=0.4.2; extra == 'advanced'
Requires-Dist: bitsandbytes>=0.41.1; extra == 'advanced'
Requires-Dist: einops>=0.6.1; extra == 'advanced'
Requires-Dist: guidance>=0.0.64; extra == 'advanced'
Requires-Dist: optimum>=1.12.0; extra == 'advanced'
Requires-Dist: peft>=0.5.0; extra == 'advanced'
Requires-Dist: pre-commit>=3.3.3; extra == 'advanced'
Requires-Dist: pyrootutils>=1.0.4; extra == 'advanced'
Requires-Dist: rich<13.0.0,>=12.6.0; extra == 'advanced'
Requires-Dist: sentencepiece>=0.1.99; extra == 'advanced'
Requires-Dist: torch==2.*; extra == 'advanced'
Requires-Dist: transformers>=4.33.0; extra == 'advanced'
Provides-Extra: dev
Requires-Dist: hydra-colorlog==1.*; extra == 'dev'
Requires-Dist: hydra-core==1.*; extra == 'dev'
Requires-Dist: hydra-optuna-sweeper==1.*; extra == 'dev'
Requires-Dist: ipykernel>=6.29.3; extra == 'dev'
Requires-Dist: lightning>=2.0.0; extra == 'dev'
Requires-Dist: torchmetrics>=0.11.4; extra == 'dev'
Requires-Dist: wandb>=0.15.5; extra == 'dev'
Provides-Extra: huggingface
Requires-Dist: llama-index-embeddings-huggingface>=0.1.3; extra == 'huggingface'
Requires-Dist: llama-index-llms-huggingface>=0.1.3; extra == 'huggingface'
Provides-Extra: tests
Requires-Dist: duckduckgo-search>=4.5.0; extra == 'tests'
Requires-Dist: pytest-asyncio>=0.23.5; extra == 'tests'
Requires-Dist: pytest-cov[toml]>=4.1.0; extra == 'tests'
Requires-Dist: pytest>=8.0.2; extra == 'tests'
Requires-Dist: sentence-transformers>=2.2.2; extra == 'tests'
Requires-Dist: torchvision>=0.17.1; extra == 'tests'
Requires-Dist: wikipedia>=1.4.0; extra == 'tests'
